{"loss": 0.5277673602104187, "learn_steps": 50, "num_params": 2668, "timestamp": 1719776383, "checkpoint_dir_name": "checkpoint_000000", "should_checkpoint": true, "done": false, "training_iteration": 1, "trial_id": "8df850f7", "date": "2024-06-30_21-39-43", "time_this_iter_s": 110.75268054008484, "time_total_s": 110.75268054008484, "pid": 545843, "hostname": "lsrosaDiag", "node_ip": "10.10.158.167", "config": {"lr": 0.00012322893226599622, "nh": 3, "sh": 32, "batch_size": 32}, "time_since_restore": 110.75268054008484, "iterations_since_restore": 1}
{"loss": 0.3990314304828644, "learn_steps": 100, "num_params": 2668, "timestamp": 1719776492, "checkpoint_dir_name": "checkpoint_000001", "should_checkpoint": true, "done": false, "training_iteration": 2, "trial_id": "8df850f7", "date": "2024-06-30_21-41-32", "time_this_iter_s": 109.03793025016785, "time_total_s": 219.79061079025269, "pid": 545843, "hostname": "lsrosaDiag", "node_ip": "10.10.158.167", "config": {"lr": 0.00012322893226599622, "nh": 3, "sh": 32, "batch_size": 32}, "time_since_restore": 219.79061079025269, "iterations_since_restore": 2}
{"loss": 0.31079497933387756, "learn_steps": 150, "num_params": 2668, "timestamp": 1719776602, "checkpoint_dir_name": "checkpoint_000002", "should_checkpoint": true, "done": false, "training_iteration": 3, "trial_id": "8df850f7", "date": "2024-06-30_21-43-22", "time_this_iter_s": 109.30938458442688, "time_total_s": 329.09999537467957, "pid": 545843, "hostname": "lsrosaDiag", "node_ip": "10.10.158.167", "config": {"lr": 0.00012322893226599622, "nh": 3, "sh": 32, "batch_size": 32}, "time_since_restore": 329.09999537467957, "iterations_since_restore": 3}
{"loss": 0.255075603723526, "learn_steps": 200, "num_params": 2668, "timestamp": 1719776712, "checkpoint_dir_name": "checkpoint_000003", "should_checkpoint": true, "done": false, "training_iteration": 4, "trial_id": "8df850f7", "date": "2024-06-30_21-45-12", "time_this_iter_s": 110.0645399093628, "time_total_s": 439.16453528404236, "pid": 545843, "hostname": "lsrosaDiag", "node_ip": "10.10.158.167", "config": {"lr": 0.00012322893226599622, "nh": 3, "sh": 32, "batch_size": 32}, "time_since_restore": 439.16453528404236, "iterations_since_restore": 4}
{"loss": 0.222211092710495, "learn_steps": 250, "num_params": 2668, "timestamp": 1719776821, "checkpoint_dir_name": "checkpoint_000004", "should_checkpoint": true, "done": true, "training_iteration": 5, "trial_id": "8df850f7", "date": "2024-06-30_21-47-01", "time_this_iter_s": 109.35242462158203, "time_total_s": 548.5169599056244, "pid": 545843, "hostname": "lsrosaDiag", "node_ip": "10.10.158.167", "config": {"lr": 0.00012322893226599622, "nh": 3, "sh": 32, "batch_size": 32}, "time_since_restore": 548.5169599056244, "iterations_since_restore": 5}
