{"loss": 0.07439780980348587, "learn_steps": 50, "num_params": 3256, "timestamp": 1720520567, "checkpoint_dir_name": "checkpoint_000000", "should_checkpoint": true, "done": false, "training_iteration": 1, "trial_id": "ea891445", "date": "2024-07-09_12-22-47", "time_this_iter_s": 114.5491623878479, "time_total_s": 114.5491623878479, "pid": 853944, "hostname": "lsrosaDiag", "node_ip": "10.10.158.167", "config": {"lr": 0.00035019345917352115, "nh": 6, "sh": 16, "batch_size": 64}, "time_since_restore": 114.5491623878479, "iterations_since_restore": 1}
{"loss": 0.054721999913454056, "learn_steps": 100, "num_params": 3256, "timestamp": 1720520682, "checkpoint_dir_name": "checkpoint_000001", "should_checkpoint": true, "done": false, "training_iteration": 2, "trial_id": "ea891445", "date": "2024-07-09_12-24-42", "time_this_iter_s": 115.39928793907166, "time_total_s": 229.94845032691956, "pid": 853944, "hostname": "lsrosaDiag", "node_ip": "10.10.158.167", "config": {"lr": 0.00035019345917352115, "nh": 6, "sh": 16, "batch_size": 64}, "time_since_restore": 229.94845032691956, "iterations_since_restore": 2}
{"loss": 0.04903612658381462, "learn_steps": 150, "num_params": 3256, "timestamp": 1720520800, "checkpoint_dir_name": "checkpoint_000002", "should_checkpoint": true, "done": false, "training_iteration": 3, "trial_id": "ea891445", "date": "2024-07-09_12-26-40", "time_this_iter_s": 118.20923852920532, "time_total_s": 348.1576888561249, "pid": 853944, "hostname": "lsrosaDiag", "node_ip": "10.10.158.167", "config": {"lr": 0.00035019345917352115, "nh": 6, "sh": 16, "batch_size": 64}, "time_since_restore": 348.1576888561249, "iterations_since_restore": 3}
{"loss": 0.04440701752901077, "learn_steps": 200, "num_params": 3256, "timestamp": 1720520916, "checkpoint_dir_name": "checkpoint_000003", "should_checkpoint": true, "done": false, "training_iteration": 4, "trial_id": "ea891445", "date": "2024-07-09_12-28-36", "time_this_iter_s": 115.99416017532349, "time_total_s": 464.15184903144836, "pid": 853944, "hostname": "lsrosaDiag", "node_ip": "10.10.158.167", "config": {"lr": 0.00035019345917352115, "nh": 6, "sh": 16, "batch_size": 64}, "time_since_restore": 464.15184903144836, "iterations_since_restore": 4}
{"loss": 0.04297908395528793, "learn_steps": 250, "num_params": 3256, "timestamp": 1720521029, "checkpoint_dir_name": "checkpoint_000004", "should_checkpoint": true, "done": true, "training_iteration": 5, "trial_id": "ea891445", "date": "2024-07-09_12-30-29", "time_this_iter_s": 112.44391655921936, "time_total_s": 576.5957655906677, "pid": 853944, "hostname": "lsrosaDiag", "node_ip": "10.10.158.167", "config": {"lr": 0.00035019345917352115, "nh": 6, "sh": 16, "batch_size": 64}, "time_since_restore": 576.5957655906677, "iterations_since_restore": 5}
