{"loss": 0.31918084621429443, "learn_steps": 50, "num_params": 4884, "timestamp": 1720471894, "checkpoint_dir_name": "checkpoint_000000", "should_checkpoint": true, "done": false, "training_iteration": 1, "trial_id": "94653391", "date": "2024-07-08_22-51-34", "time_this_iter_s": 126.25316905975342, "time_total_s": 126.25316905975342, "pid": 834279, "hostname": "lsrosaDiag", "node_ip": "10.10.158.167", "config": {"lr": 2.4761301914593212e-05, "nh": 6, "sh": 16, "batch_size": 32}, "time_since_restore": 126.25316905975342, "iterations_since_restore": 1}
{"loss": 0.24995705485343933, "learn_steps": 100, "num_params": 4884, "timestamp": 1720472018, "checkpoint_dir_name": "checkpoint_000001", "should_checkpoint": true, "done": false, "training_iteration": 2, "trial_id": "94653391", "date": "2024-07-08_22-53-38", "time_this_iter_s": 123.58105158805847, "time_total_s": 249.8342206478119, "pid": 834279, "hostname": "lsrosaDiag", "node_ip": "10.10.158.167", "config": {"lr": 2.4761301914593212e-05, "nh": 6, "sh": 16, "batch_size": 32}, "time_since_restore": 249.8342206478119, "iterations_since_restore": 2}
{"loss": 0.21151700615882874, "learn_steps": 150, "num_params": 4884, "timestamp": 1720472143, "checkpoint_dir_name": "checkpoint_000002", "should_checkpoint": true, "done": false, "training_iteration": 3, "trial_id": "94653391", "date": "2024-07-08_22-55-43", "time_this_iter_s": 125.21582508087158, "time_total_s": 375.0500457286835, "pid": 834279, "hostname": "lsrosaDiag", "node_ip": "10.10.158.167", "config": {"lr": 2.4761301914593212e-05, "nh": 6, "sh": 16, "batch_size": 32}, "time_since_restore": 375.0500457286835, "iterations_since_restore": 3}
{"loss": 0.1870652437210083, "learn_steps": 200, "num_params": 4884, "timestamp": 1720472267, "checkpoint_dir_name": "checkpoint_000003", "should_checkpoint": true, "done": false, "training_iteration": 4, "trial_id": "94653391", "date": "2024-07-08_22-57-47", "time_this_iter_s": 124.07038474082947, "time_total_s": 499.12043046951294, "pid": 834279, "hostname": "lsrosaDiag", "node_ip": "10.10.158.167", "config": {"lr": 2.4761301914593212e-05, "nh": 6, "sh": 16, "batch_size": 32}, "time_since_restore": 499.12043046951294, "iterations_since_restore": 4}
{"loss": 0.1663251668214798, "learn_steps": 250, "num_params": 4884, "timestamp": 1720472388, "checkpoint_dir_name": "checkpoint_000004", "should_checkpoint": true, "done": true, "training_iteration": 5, "trial_id": "94653391", "date": "2024-07-08_22-59-48", "time_this_iter_s": 120.85240626335144, "time_total_s": 619.9728367328644, "pid": 834279, "hostname": "lsrosaDiag", "node_ip": "10.10.158.167", "config": {"lr": 2.4761301914593212e-05, "nh": 6, "sh": 16, "batch_size": 32}, "time_since_restore": 619.9728367328644, "iterations_since_restore": 5}
