{"loss": 0.1731332242488861, "learn_steps": 50, "num_params": 13720, "timestamp": 1720521716, "checkpoint_dir_name": "checkpoint_000000", "should_checkpoint": true, "done": false, "training_iteration": 1, "trial_id": "880068a0", "date": "2024-07-09_12-41-56", "time_this_iter_s": 115.1633710861206, "time_total_s": 115.1633710861206, "pid": 854502, "hostname": "lsrosaDiag", "node_ip": "10.10.158.167", "config": {"lr": 3.954610205617632e-05, "nh": 7, "sh": 32, "batch_size": 8}, "time_since_restore": 115.1633710861206, "iterations_since_restore": 1}
{"loss": 0.11532139778137207, "learn_steps": 100, "num_params": 13720, "timestamp": 1720521828, "checkpoint_dir_name": "checkpoint_000001", "should_checkpoint": true, "done": false, "training_iteration": 2, "trial_id": "880068a0", "date": "2024-07-09_12-43-48", "time_this_iter_s": 111.64939284324646, "time_total_s": 226.81276392936707, "pid": 854502, "hostname": "lsrosaDiag", "node_ip": "10.10.158.167", "config": {"lr": 3.954610205617632e-05, "nh": 7, "sh": 32, "batch_size": 8}, "time_since_restore": 226.81276392936707, "iterations_since_restore": 2}
{"loss": 0.08881153166294098, "learn_steps": 150, "num_params": 13720, "timestamp": 1720521942, "checkpoint_dir_name": "checkpoint_000002", "should_checkpoint": true, "done": false, "training_iteration": 3, "trial_id": "880068a0", "date": "2024-07-09_12-45-42", "time_this_iter_s": 114.08504509925842, "time_total_s": 340.8978090286255, "pid": 854502, "hostname": "lsrosaDiag", "node_ip": "10.10.158.167", "config": {"lr": 3.954610205617632e-05, "nh": 7, "sh": 32, "batch_size": 8}, "time_since_restore": 340.8978090286255, "iterations_since_restore": 3}
{"loss": 0.07531827688217163, "learn_steps": 200, "num_params": 13720, "timestamp": 1720522057, "checkpoint_dir_name": "checkpoint_000003", "should_checkpoint": true, "done": false, "training_iteration": 4, "trial_id": "880068a0", "date": "2024-07-09_12-47-37", "time_this_iter_s": 115.4052062034607, "time_total_s": 456.3030152320862, "pid": 854502, "hostname": "lsrosaDiag", "node_ip": "10.10.158.167", "config": {"lr": 3.954610205617632e-05, "nh": 7, "sh": 32, "batch_size": 8}, "time_since_restore": 456.3030152320862, "iterations_since_restore": 4}
{"loss": 0.06765139102935791, "learn_steps": 250, "num_params": 13720, "timestamp": 1720522172, "checkpoint_dir_name": "checkpoint_000004", "should_checkpoint": true, "done": true, "training_iteration": 5, "trial_id": "880068a0", "date": "2024-07-09_12-49-32", "time_this_iter_s": 114.77004814147949, "time_total_s": 571.0730633735657, "pid": 854502, "hostname": "lsrosaDiag", "node_ip": "10.10.158.167", "config": {"lr": 3.954610205617632e-05, "nh": 7, "sh": 32, "batch_size": 8}, "time_since_restore": 571.0730633735657, "iterations_since_restore": 5}
